ldapauthbackend/__init__.py
ldapauthbackend/admin.py
ldapauthbackend/apps.py
ldapauthbackend/backend.py
ldapauthbackend/models.py
ldapauthbackend/operations.py
ldapauthbackend/tests.py
ldapauthbackend/urls.py
ldapauthbackend/views.py
ldapauthbackend/angularhostpages/ldapauthbackend/index.html
ldapauthbackend/migrations/0001_initial.py
ldapauthbackend/migrations/0002_ldapuserprofile_import_staff.py
ldapauthbackend/migrations/0003_auto_20180912_0807.py
ldapauthbackend/migrations/0004_auto_20180919_0633.py
ldapauthbackend/migrations/__init__.py
ldapauthbackend/static/ldapauthbackend/ui/3rdpartylicenses.txt
ldapauthbackend/static/ldapauthbackend/ui/MaterialIcons-Regular.012cf6a10129e2275d79.woff
ldapauthbackend/static/ldapauthbackend/ui/MaterialIcons-Regular.570eb83859dc23dd0eec.woff2
ldapauthbackend/static/ldapauthbackend/ui/MaterialIcons-Regular.a37b0c01c0baf1888ca8.ttf
ldapauthbackend/static/ldapauthbackend/ui/MaterialIcons-Regular.e79bfd88537def476913.eot
ldapauthbackend/static/ldapauthbackend/ui/favicon.ico
ldapauthbackend/static/ldapauthbackend/ui/main.592fcffca0831c3b7e08.js
ldapauthbackend/static/ldapauthbackend/ui/polyfills.6a4ec4295cccf8570371.js
ldapauthbackend/static/ldapauthbackend/ui/roboto-latin-100.987b84570ea69ee66045.woff2
ldapauthbackend/static/ldapauthbackend/ui/roboto-latin-100.e9dbbe8a693dd275c16d.woff
ldapauthbackend/static/ldapauthbackend/ui/roboto-latin-100italic.6232f43d15b0e7a0bf0f.woff2
ldapauthbackend/static/ldapauthbackend/ui/roboto-latin-100italic.d704bb3d579b7d5e4088.woff
ldapauthbackend/static/ldapauthbackend/ui/roboto-latin-300.55536c8e9e9a532651e3.woff2
ldapauthbackend/static/ldapauthbackend/ui/roboto-latin-300.a1471d1d6431c893582a.woff
ldapauthbackend/static/ldapauthbackend/ui/roboto-latin-300italic.210a7c781f5a354a0e49.woff
ldapauthbackend/static/ldapauthbackend/ui/roboto-latin-300italic.d69924b98acd849cdeba.woff2
ldapauthbackend/static/ldapauthbackend/ui/roboto-latin-400.5d4aeb4e5f5ef754e307.woff2
django_ldap_auth_backend-0.3.3.dist-info/METADATA
django_ldap_auth_backend-0.3.3.dist-info/WHEEL
django_ldap_auth_backend-0.3.3.dist-info/top_level.txt
django_ldap_auth_backend-0.3.3.dist-info/RECORD
