Metadata-Version: 2.1
Name: django-ldap-auth-backend
Version: 0.3.3
Summary: LDAP authentication backend for Django
License: MIT License
Platform: UNKNOWN
Classifier: Development Status :: 5 - Production/Stable
Classifier: Intended Audience :: Developers
Classifier: License :: OSI Approved :: MIT License
Classifier: Programming Language :: Python :: 3.7
Classifier: Framework :: Django :: 3.2
Requires-Dist: python-ldap (<4.0.0,>=3.4.0)
Requires-Dist: django-angular-host-page-template-backend (<0.4.0,>=0.3.0)
